{
  "flavia": {
    "nome": "Flavia Quintino",
    "foto": "assets/revendedores/flavia.jpg"
  },
  "larissaaraujocerqueira": {
    "nome": "Larissa Araujo",
    "foto": "assets/revendedores/larissaaraujocerqueira.jpg"
  },
  "anapauladasilva": {
    "nome": "Ana Paula",
    "foto": "assets/revendedores/anapauladasilva.jpg"
  },
    "carol": {
    "nome": "Adhelaine Caroline",
    "foto": "assets/revendedores/carol.jpg"
  },
    "denisegil": {
    "nome": "Denise Gil",
    "foto": "assets/revendedores/denisegil.jpg"
  },
    "rosangeladossantos": {
    "nome": "Rosângela dos Santos",
    "foto": "assets/revendedores/rosangeladossantos.jpg"
  },
    "tiakaka": {
    "nome": "Tia KaKa",
    "foto": "assets/revendedores/tiakaka.jpg"
  },
    "willianjefferson": {
    "nome": "Willian Jefferson",
    "foto": "assets/revendedores/willianjefferson.jpg"
  },
    "elizabethrodrigues": {
    "nome": "Elizabeth Rodrigues",
    "foto": "assets/revendedores/elizabethrodrigues.jpg"
  },
    "arliaraujo": {
    "nome": "Arli Araújo",
    "foto": "assets/revendedores/arliaraujo.jpg"
  },
    "tinabrum": {
    "nome": "Tina Brum",
    "foto": "assets/revendedores/tinabrum.jpg"
  },
    "mariajose": {
    "nome": "Maria José",
    "foto": "assets/revendedores/mariajose.jpg"
  },
    "praidalinacoata": {
    "nome": "Prª Idalina Coata",
    "foto": "assets/revendedores/praidalinacoata.jpg"
  }
}
